quickplotlib/__init__.py
quickplotlib/viz.py
quickplotlib-0.3.dist-info/LICENSE
quickplotlib-0.3.dist-info/METADATA
quickplotlib-0.3.dist-info/WHEEL
quickplotlib-0.3.dist-info/top_level.txt
quickplotlib-0.3.dist-info/RECORD
